cother_agent.cpython-37m-darwin.so
gym_fearbun/__init__.py
gym_fearbun/envs/__init__.py
gym_fearbun/envs/raceboard/__init__.py
gym_fearbun/envs/raceboard/c_raceboard.c
gym_fearbun/envs/raceboard/c_raceboard.cpython-37m-darwin.so
gym_fearbun/envs/raceboard/raceboard.py
gym_fearbun/envs/raceboard/maps/map1.txt
gym_fearbun/envs/raceboard/maps/map2.txt
gym_fearbun/envs/raceboard/maps/small_map1.txt
gym_fearbun-0.0.41.dist-info/LICENSE
gym_fearbun-0.0.41.dist-info/METADATA
gym_fearbun-0.0.41.dist-info/WHEEL
gym_fearbun-0.0.41.dist-info/top_level.txt
gym_fearbun-0.0.41.dist-info/RECORD
