Metadata-Version: 2.1
Name: gym-fearbun
Version: 0.0.41
Summary: UNKNOWN
Home-page: https://github.com/rolypolyvg295/gym_fearbun/tree/master/gym_fearbun
Author: UNKNOWN
Author-email: UNKNOWN
License: MIT
Platform: UNKNOWN
Requires-Dist: gym
Requires-Dist: six
Requires-Dist: Cython
Requires-Dist: numpy
